timesweeper/__init__.py
timesweeper/__main__.py
timesweeper/cli.py
timesweeper/convert_syncfiles.py
timesweeper/find_sweeps_npz.py
timesweeper/find_sweeps_vcf.py
timesweeper/make_training_features.py
timesweeper/merge_logs_acc.py
timesweeper/models.py
timesweeper/net_hyper_tuning.py
timesweeper/parse_slim_logs.py
timesweeper/process_vcfs.py
timesweeper/simulate_custom.py
timesweeper/simulate_stdpopsim.py
timesweeper/tp1_model.py
timesweeper/train_nets.py
timesweeper/train_nets_shic.py
timesweeper/train_shoulder_nets.py
Timesweeper-1.4.dist-info/LICENSE
Timesweeper-1.4.dist-info/METADATA
Timesweeper-1.4.dist-info/WHEEL
Timesweeper-1.4.dist-info/entry_points.txt
Timesweeper-1.4.dist-info/top_level.txt
Timesweeper-1.4.dist-info/RECORD
